adbookfromkevin/__init__.py
adbookfromkevin/adbookfromkevin.py
adbookfromkevin-0.0.1.dist-info/LICENSE.txt
adbookfromkevin-0.0.1.dist-info/METADATA
adbookfromkevin-0.0.1.dist-info/WHEEL
adbookfromkevin-0.0.1.dist-info/top_level.txt
adbookfromkevin-0.0.1.dist-info/RECORD
