Metadata-Version: 2.1
Name: adbookfromkevin
Version: 0.0.1
Summary: A small example address book package
Home-page: https://github.com/Julian-Spring-2022/stack-machine-kevingzr-gsb
Author: Zhirong (Kevin) Guo
Author-email: zguo22@gsb.columbia.edu
License: UNKNOWN
Project-URL: Bug Tracker, https://github.com/Julian-Spring-2022/stack-machine-kevingzr-gsb
Platform: UNKNOWN
Classifier: Programming Language :: Python :: 3
Classifier: License :: OSI Approved :: MIT License
Classifier: Operating System :: OS Independent
Requires-Python: >=3.6
License-File: LICENSE.txt
